[
  {
    "external_id": "METFORMIN",
    "analyte_number": null,
    "short_number": null,
    "long_number": null,
    "inn": "Metformin",
    "unii": {
      "substance_unii": "9100L32L2N"
    }
  },
  {
    "external_id": "NPH INSULIN",
    "analyte_number": "AN000045",
    "short_number": "NNC0121",
    "long_number": "NNC0121-0000-0308",
    "inn": "NPH Insulin",
    "unii": {
      "substance_unii": "1Y17CTI5SR"
    }
  },
  {
    "external_id": "semaglutide",
    "analyte_number": "AN000028",
    "short_number": "NNC0113-0217",
    "long_number": "NNC 0113-0000-0217",
    "inn": "semaglutide",
    "unii": {
      "substance_unii": "53AXN4NNHX"
    }
  },
  {
    "external_id": "cagrilintide",
    "analyte_number": "AN000070",
    "short_number": "NNC0174-0833",
    "long_number": "NNC 0174-0000-0833",
    "inn": "cagrilintide",
    "unii": {
      "substance_unii": "AO43BIF1U8"
    }
  }
]