{
  "items": [
    {
      "acceptedVersion": false,
      "changeType": null,
      "code": "CTTerm_000164",
      "description": null,
      "elementColour": null,
      "elementSubType": {
        "catalogueName": "SDTM CT",
        "changeDescription": "Approved version",
        "codelistUid": "CTCodelist_000024",
        "endDate": null,
        "libraryName": "Sponsor",
        "order": 1,
        "possibleActions": [
          "inactivate",
          "newVersion"
        ],
        "sponsorPreferredName": "Screening",
        "sponsorPreferredNameSentenceCase": "screening",
        "startDate": "2022-07-06T19:27:09.760372",
        "status": "Final",
        "termUid": "CTTerm_000169",
        "userInitials": "unknown-user",
        "version": "1.0"
      },
      "elementUid": "StudyElement_000015",
      "endDate": null,
      "endRule": null,
      "name": "Screening",
      "order": 1,
      "plannedDuration": null,
      "shortName": "Screening",
      "startDate": "2022-07-12T06:08:48.500388",
      "startRule": null,
      "status": null,
      "studyCompoundDosingCount": 0,
      "studyUid": "Study_000002",
      "userInitials": "MT"
    },
    {
      "acceptedVersion": false,
      "changeType": null,
      "code": "CTTerm_000163",
      "description": null,
      "elementColour": null,
      "elementSubType": {
        "catalogueName": "SDTM CT",
        "changeDescription": "Approved version",
        "codelistUid": "CTCodelist_000024",
        "endDate": null,
        "libraryName": "Sponsor",
        "order": 3,
        "possibleActions": [
          "inactivate",
          "newVersion"
        ],
        "sponsorPreferredName": "Treatment",
        "sponsorPreferredNameSentenceCase": "treatment",
        "startDate": "2022-07-06T19:27:09.348270",
        "status": "Final",
        "termUid": "CTTerm_000167",
        "userInitials": "unknown-user",
        "version": "1.0"
      },
      "elementUid": "StudyElement_000017",
      "endDate": null,
      "endRule": null,
      "name": "NPH insulin",
      "order": 2,
      "plannedDuration": null,
      "shortName": "NPH insulin",
      "startDate": "2022-07-12T06:09:09.343754",
      "startRule": null,
      "status": null,
      "studyCompoundDosingCount": 0,
      "studyUid": "Study_000002",
      "userInitials": "MT"
    },
    {
      "acceptedVersion": false,
      "changeType": null,
      "code": "CTTerm_000163",
      "description": null,
      "elementColour": null,
      "elementSubType": {
        "catalogueName": "SDTM CT",
        "changeDescription": "Approved version",
        "codelistUid": "CTCodelist_000024",
        "endDate": null,
        "libraryName": "Sponsor",
        "order": 3,
        "possibleActions": [
          "inactivate",
          "newVersion"
        ],
        "sponsorPreferredName": "Treatment",
        "sponsorPreferredNameSentenceCase": "treatment",
        "startDate": "2022-07-06T19:27:09.348270",
        "status": "Final",
        "termUid": "CTTerm_000167",
        "userInitials": "unknown-user",
        "version": "1.0"
      },
      "elementUid": "StudyElement_000019",
      "endDate": null,
      "endRule": null,
      "name": "Metformin",
      "order": 3,
      "plannedDuration": null,
      "shortName": "Metformin",
      "startDate": "2022-07-12T06:09:25.493108",
      "startRule": null,
      "status": null,
      "studyCompoundDosingCount": 0,
      "studyUid": "Study_000002",
      "userInitials": "MT"
    },
    {
      "acceptedVersion": false,
      "changeType": null,
      "code": "CTTerm_000164",
      "description": null,
      "elementColour": null,
      "elementSubType": {
        "catalogueName": "SDTM CT",
        "changeDescription": "Approved version",
        "codelistUid": "CTCodelist_000024",
        "endDate": null,
        "libraryName": "Sponsor",
        "order": 5,
        "possibleActions": [
          "inactivate",
          "newVersion"
        ],
        "sponsorPreferredName": "Follow-up",
        "sponsorPreferredNameSentenceCase": "follow-up",
        "startDate": "2022-07-06T19:27:09.495223",
        "status": "Final",
        "termUid": "CTTerm_000168",
        "userInitials": "unknown-user",
        "version": "1.0"
      },
      "elementUid": "StudyElement_000021",
      "endDate": null,
      "endRule": null,
      "name": "Follow-up",
      "order": 4,
      "plannedDuration": null,
      "shortName": "Follow-up",
      "startDate": "2022-07-12T06:09:42.528635",
      "startRule": null,
      "status": null,
      "studyCompoundDosingCount": 0,
      "studyUid": "Study_000002",
      "userInitials": "MT"
    }
  ],
  "page": 1,
  "size": 0,
  "total": 0
}